{
  "name": "Burrowing creature",
  "type": "tool",
  "img": "icons/svg/item-bag.svg",
  "system": {
    "type": "common",
    "loadout": 1,
    "equipped": false,
    "broken": false,
    "description": ""
  },
  "effects": [],
  "folder": "NcgbA8U9Rw40owzs",
  "ownership": {
    "default": 0,
    "hzjhFMblPzYeVvdR": 3
  },
  "flags": {},
  "_stats": {
    "compendiumSource": null,
    "duplicateSource": null,
    "coreVersion": "12.330",
    "systemId": "teeth",
    "systemVersion": "0.1",
    "createdTime": 1721138995176,
    "modifiedTime": 1722986702765,
    "lastModifiedBy": "78NHFd7NStjLGK2G"
  },
  "_id": "NFF3sxokAG9VJHqi",
  "sort": 200000,
  "_key": "!items!NFF3sxokAG9VJHqi"
}
